<?xml version="1.0" encoding="UTF-8"?>
<metadata xml:lang="en"><Esri><CreaDate>20171110</CreaDate><CreaTime>21393600</CreaTime><ArcGISFormat>1.0</ArcGISFormat><SyncOnce>TRUE</SyncOnce><DataProperties><lineage><Process ToolSource="c:\program files (x86)\arcgis\desktop10.5\ArcToolbox\Toolboxes\Data Management Tools.tbx\MosaicToNewRaster" Date="20171110" Time="213941">MosaicToNewRaster cv;cc;ss;si;sc;ns;ni;ncw;ncm;nce;gb "D:\ml with cdec uf\Input Data\CALVEG" calveg_raster.tif # 8_BIT_UNSIGNED # 1 LAST MATCH</Process></lineage></DataProperties></Esri></metadata>
